fastapi_sqlalchemy/__init__.py
fastapi_sqlalchemy/exceptions.py
fastapi_sqlalchemy/middleware.py
fastapi_sqlalchemy/py.typed
FastAPI_SQLAlchemy-0.2.1.dist-info/LICENSE
FastAPI_SQLAlchemy-0.2.1.dist-info/METADATA
FastAPI_SQLAlchemy-0.2.1.dist-info/WHEEL
FastAPI_SQLAlchemy-0.2.1.dist-info/top_level.txt
FastAPI_SQLAlchemy-0.2.1.dist-info/RECORD
