Metadata-Version: 1.2
Name: FastAPI-SQLAlchemy
Version: 0.2.1
Summary: Adds simple SQLAlchemy support to FastAPI
Home-page: https://github.com/mfreeborn/fastapi-sqlalchemy
Author: Michael Freeborn
Author-email: michaelfreeborn1@gmail.com
License: MIT
Project-URL: Code, https://github.com/mfreeborn/fastapi-sqlalchemy
Project-URL: Issue tracker, https://github.com/mfreeborn/fastapi-sqlalchemy/issues
Platform: UNKNOWN
Classifier: Development Status :: 4 - Beta
Classifier: Environment :: Web Environment
Classifier: Framework :: AsyncIO
Classifier: Intended Audience :: Developers
Classifier: License :: OSI Approved :: MIT License
Classifier: Operating System :: OS Independent
Classifier: Programming Language :: Python :: 3.6
Classifier: Programming Language :: Python :: 3.7
Classifier: Programming Language :: Python :: 3.8
Classifier: Programming Language :: Python :: 3 :: Only
Classifier: Programming Language :: Python :: Implementation :: CPython
Classifier: Topic :: Internet :: WWW/HTTP :: HTTP Servers
Classifier: Topic :: Internet :: WWW/HTTP :: Dynamic Content
Classifier: Topic :: Software Development :: Libraries :: Python Modules
Requires-Python: >=3.7
